setup.cfg
setup.py
Fragment_Service_Provider.egg-info/PKG-INFO
Fragment_Service_Provider.egg-info/SOURCES.txt
Fragment_Service_Provider.egg-info/dependency_links.txt
Fragment_Service_Provider.egg-info/namespace_packages.txt
Fragment_Service_Provider.egg-info/requires.txt
Fragment_Service_Provider.egg-info/top_level.txt
sdh/__init__.py
sdh/fragments/__init__.py
sdh/fragments/jobs/__init__.py
sdh/fragments/jobs/collect.py
sdh/fragments/jobs/query.py
sdh/fragments/server/__init__.py
sdh/fragments/server/base.py