Metadata-Version: 1.1
Name: Fragment-Service-Provider
Version: 0.1.1
Summary: A library for making web services built on the SDH Fragment Provider
Home-page: https://github.com/smartdeveloperhub/fragment-service-provider
Author: Fernando Serena
Author-email: fernando.serena@centeropenmiddleware.com
License: Apache 2
Download-URL: https://github.com/smartdeveloperhub/fragment-service-provider/tarball/0.0.8
Keywords: linked-data,path,ontology,plan
Platform: UNKNOWN
